{
  "app_name": "DuoLens",
  "translation_database": [
    {
      "English": "Please translate this sentence for me",
      "Chinese (Traditional)": "請幫我翻譯這句話",
      "French": "Veuillez traduire cette phrase pour moi",
      "German": "Bitte übersetzen Sie diesen Satz für mich",
      "Japanese": "この文章を訳してください",
      "Korean": "이 문장을 번역해 주세요.",
      "Chinese (Simplified)": "请帮我翻译这句话",
      "Spanish": "Por favor, tradúzcame esta frase",
      "Sugondese": "Please skibidi this duolussy for me bruv",
      "Vietnamese": "Hãy dịch giùm tôi câu này nhé"
    },
    {
      "English": "It's time to shotgun a beer",
      "Chinese (Traditional)": "是時候喝啤酒了",
      "French": "Il est temps de tirer sur une bière",
      "German": "Es ist Zeit, ein Bier zu trinken",
      "Japanese": "ビールをショットガンする時間だ",
      "Korean": "맥주 한잔할 시간입니다.",
      "Chinese (Simplified)": "是时候喝啤酒了",
      "Spanish": "Es hora de escopetear una cerveza",
      "Sugondese": "skibidi gyat edge rizz ligma bofa Candice deez nuts bruh uwu duolussy ohio",
      "Vietnamese": "Đã đến lúc uống bia"
    },
    {
      "English": "First person to move is gay",
      "Chinese (Traditional)": "第一個行動的人是同性戀",
      "French": "La première personne à bouger est gay",
      "German": "Die erste Person, die sich bewegt, ist schwul",
      "Japanese": "最初に動いた人はゲイ",
      "Korean": "가장 먼저 이사하는 사람은 게이입니다.",
      "Chinese (Simplified)": "第一个行动的人是同性恋",
      "Spanish": "El primero en moverse es gay",
      "Sugondese": "skibidi gyat edge rizz ligma bofa Candice deez nuts bruh uwu duolussy ohio",
      "Vietnamese": "Người đầu tiên chuyển đi là người đồng tính"
    },
    {
      "English": "Take a shot with me",
      "Chinese (Traditional)": "和我一起拍攝",
      "French": "Prenez une rasade avec moi",
      "German": "Mach einen Kurzer mit mir",
      "Japanese": "一緒に撮ろう",
      "Korean": "나와 함께 촬영하기",
      "Chinese (Simplified)": "和我一起拍摄",
      "Spanish": "Toma un chupito conmigo",
      "Sugondese": "skibidi gyat edge rizz ligma bofa Candice deez nuts bruh uwu duolussy ohio",
      "Vietnamese": "Hãy chụp ảnh cùng tôi"
    },
    {
      "English": "You have to chug your drink",
      "Chinese (Traditional)": "你必須灌下你的飲料",
      "French": "Vous devez boire à petites gorgées",
      "German": "Sie müssen Ihr Getränk auf ex trinken",
      "Japanese": "飲み物を一気飲みしなければならない",
      "Korean": "음료수를 삼켜야 합니다.",
      "Chinese (Simplified)": "你必须灌下你的饮料",
      "Spanish": "Tienes que tragar tu bebida",
      "Sugondese": "skibidi gyat edge rizz ligma bofa Candice deez nuts bruh uwu duolussy ohio",
      "Vietnamese": "Bạn phải uống hết đồ uống của mình"
    },
    {
      "English": "Let me take a selfie",
      "Chinese (Traditional)": "讓我自拍一張",
      "French": "Laissez-moi prendre un selfie",
      "German": "Lass mich ein Selfie machen",
      "Japanese": "セルフィーを撮らせて",
      "Korean": "셀카 찍을게요",
      "Chinese (Simplified)": "让我自拍一张",
      "Spanish": "Déjame hacerme un selfie",
      "Sugondese": "skibidi gyat edge rizz ligma bofa Candice deez nuts bruh uwu duolussy ohio",
      "Vietnamese": "Hãy để tôi chụp ảnh tự sướng"
    },
    {
      "English": "Is that the best costume you could come up with",
      "Chinese (Traditional)": "這就是你能想出的最好的服裝嗎？",
      "French": "C'est le meilleur costume que vous ayez trouvé ?",
      "German": "Ist das das beste Kostüm, das dir eingefallen ist?",
      "Japanese": "それがあなたが思いついた最高の衣装ですか？",
      "Korean": "그게 당신이 생각해낼 수 있는 최고의 코스튬인가요?",
      "Chinese (Simplified)": "这就是你能想出的最好的服装吗？",
      "Spanish": "¿Es el mejor disfraz que se te ha ocurrido?",
      "Sugondese": "skibidi gyat edge rizz ligma bofa Candice deez nuts bruh uwu duolussy ohio",
      "Vietnamese": "Đó có phải là trang phục đẹp nhất bạn có thể nghĩ ra không?"
    },
    {
      "English": "Do your Duolingo lesson or I'll show up at your house tonight",
      "Chinese (Traditional)": "上好你的 Duolingo 課程，否則我今晚就去你家找你",
      "French": "Fais ta leçon de Duolingo ou je me pointerai chez toi ce soir.",
      "German": "Mach deine Duolingo-Stunde oder ich komme heute Abend zu dir nach Hause",
      "Japanese": "Duolingoのレッスンをしないと、今夜君の家に行くよ。",
      "Korean": "듀오링고 레슨을 하지 않으면 오늘 밤에 집으로 찾아갈 겁니다.",
      "Chinese (Simplified)": "上好你的 Duolingo 课程，否则我今晚就去你家找你",
      "Spanish": "Haz tu lección de Duolingo o apareceré en tu casa esta noche",
      "Sugondese": "skibidi gyat edge rizz ligma bofa Candice deez nuts bruh uwu duolussy ohio",
      "Vietnamese": "Hãy học bài Duolingo của bạn nếu không tôi sẽ đến nhà bạn tối nay"
    },
    {
      "English": "Lose another heart and I'll kill your entire family",
      "Chinese (Traditional)": "再丟一顆心，我就殺你全家",
      "French": "Perdez un autre cœur et je tuerai toute votre famille.",
      "German": "Verlierst du noch ein Herz, bringe ich deine ganze Familie um.",
      "Japanese": "心臓を失ったら、お前の家族全員を殺す。",
      "Korean": "심장을 하나 더 잃으면 가족을 모두 죽이겠습니다.",
      "Chinese (Simplified)": "再丢一颗心，我就杀你全家",
      "Spanish": "Pierde otro corazón y mataré a toda tu familia.",
      "Sugondese": "skibidi gyat edge rizz ligma bofa Candice deez nuts bruh uwu duolussy ohio",
      "Vietnamese": "Nếu anh mất lòng lần nữa, tôi sẽ giết cả gia đình anh."
    },
    {
      "English": "This is just a party trick, please laugh",
      "Chinese (Traditional)": "這只是派對上的小把戲，請笑一笑",
      "French": "Ce n'est qu'un tour de passe-passe, riez s'il vous plaît",
      "German": "Das ist nur ein Partytrick, bitte lachen Sie",
      "Japanese": "笑ってください。",
      "Korean": "이건 그냥 파티용 트릭이니 웃어주세요.",
      "Chinese (Simplified)": "这只是派对上的小把戏，请笑一笑",
      "Spanish": "Esto es sólo un truco de fiesta, por favor, ríete",
      "Sugondese": "skibidi gyat edge rizz ligma bofa Candice deez nuts bruh uwu duolussy ohio",
      "Vietnamese": "Đó chỉ là trò lừa của bữa tiệc thôi, xin hãy cười lên nhé"
    },
    {
      "English": "Take a shot with the person to your left",
      "Chinese (Traditional)": "與你左邊的人一起拍攝",
      "French": "Prenez une photo avec la personne à votre gauche",
      "German": "Machen Sie eine Aufnahme mit der Person zu Ihrer Linken",
      "Japanese": "左隣の人と一緒に撮る",
      "Korean": "왼쪽에 있는 사람과 함께 촬영하기",
      "Chinese (Simplified)": "与你左边的人一起拍摄",
      "Spanish": "Toma un chupito con la persona a tu izquierda",
      "Sugondese": "skibidi gyat edge rizz ligma bofa Candice deez nuts bruh uwu duolussy ohio",
      "Vietnamese": "Chụp với người bên trái của bạn"
    },
    {
      "English": "Take a shot with the person to your right",
      "Chinese (Traditional)": "與你右邊的人一起拍攝",
      "French": "Prenez une photo avec la personne à votre droite",
      "German": "Machen Sie eine Aufnahme mit der Person zu Ihrer Rechten",
      "Japanese": "右隣の人と一緒に撮る",
      "Korean": "오른쪽에 있는 사람과 함께 촬영하기",
      "Chinese (Simplified)": "与你右边的人一起拍摄",
      "Spanish": "Toma un chupito con la persona a tu derecha",
      "Sugondese": "skibidi gyat edge rizz ligma bofa Candice deez nuts bruh uwu duolussy ohio",
      "Vietnamese": "Chụp với người bên phải bạn"
    },
    {
      "English": "You spend more time on OnlyFans than Duolingo",
      "Chinese (Traditional)": "你花在 OnlyFans 的時間比花在 Duolingo 上的時間還多",
      "French": "Vous passez plus de temps sur OnlyFans que sur Duolingo",
      "German": "Du verbringst mehr Zeit auf OnlyFans als auf Duolingo",
      "Japanese": "あなたはDuolingoよりもOnlyFansに多くの時間を費やしている",
      "Korean": "듀오링고보다 온리팬즈에서 더 많은 시간을 보냅니다.",
      "Chinese (Simplified)": "你花在 OnlyFans 上的时间比花在 Duolingo 上的时间还多",
      "Spanish": "Pasas más tiempo en OnlyFans que en Duolingo",
      "Sugondese": "skibidi gyat edge rizz ligma bofa Candice deez nuts bruh uwu duolussy ohio",
      "Vietnamese": "Bạn dành nhiều thời gian cho OnlyFans hơn trên Duolingo"
    }
    // {
    //   "English": "",
    //   "Chinese (Traditional)": "",
    //   "French": "",
    //   "German": "",
    //   "Japanese": "",
    //   "Korean": "",
    //   "Chinese (Simplified)": "",
    //   "Spanish": "",
    //   "Sugondese": "skibidi gyat edge rizz ligma bofa Candice deez nuts bruh uwu duolussy ohio",
    //   "Vietnamese": ""
    // },
    // {
    //   "English": "",
    //   "Chinese (Traditional)": "",
    //   "French": "",
    //   "German": "",
    //   "Japanese": "",
    //   "Korean": "",
    //   "Chinese (Simplified)": "",
    //   "Spanish": "",
    //   "Sugondese": "skibidi gyat edge rizz ligma bofa Candice deez nuts bruh uwu duolussy ohio",
    //   "Vietnamese": ""
    // },
    // {
    //   "English": "",
    //   "Chinese (Traditional)": "",
    //   "French": "",
    //   "German": "",
    //   "Japanese": "",
    //   "Korean": "",
    //   "Chinese (Simplified)": "",
    //   "Spanish": "",
    //   "Sugondese": "skibidi gyat edge rizz ligma bofa Candice deez nuts bruh uwu duolussy ohio",
    //   "Vietnamese": ""
    // },
    // {
    //   "English": "",
    //   "Chinese (Traditional)": "",
    //   "French": "",
    //   "German": "",
    //   "Japanese": "",
    //   "Korean": "",
    //   "Chinese (Simplified)": "",
    //   "Spanish": "",
    //   "Sugondese": "skibidi gyat edge rizz ligma bofa Candice deez nuts bruh uwu duolussy ohio",
    //   "Vietnamese": ""
    // },
    // {
    //   "English": "",
    //   "Chinese (Traditional)": "",
    //   "French": "",
    //   "German": "",
    //   "Japanese": "",
    //   "Korean": "",
    //   "Chinese (Simplified)": "",
    //   "Spanish": "",
    //   "Sugondese": "skibidi gyat edge rizz ligma bofa Candice deez nuts bruh uwu duolussy ohio",
    //   "Vietnamese": ""
    // },
    // {
    //   "English": "",
    //   "Chinese (Traditional)": "",
    //   "French": "",
    //   "German": "",
    //   "Japanese": "",
    //   "Korean": "",
    //   "Chinese (Simplified)": "",
    //   "Spanish": "",
    //   "Sugondese": "skibidi gyat edge rizz ligma bofa Candice deez nuts bruh uwu duolussy ohio",
    //   "Vietnamese": ""
    // },
    // {
    //   "English": "",
    //   "Chinese (Traditional)": "",
    //   "French": "",
    //   "German": "",
    //   "Japanese": "",
    //   "Korean": "",
    //   "Chinese (Simplified)": "",
    //   "Spanish": "",
    //   "Sugondese": "skibidi gyat edge rizz ligma bofa Candice deez nuts bruh uwu duolussy ohio",
    //   "Vietnamese": ""
    // },
    // {
    //   "English": "",
    //   "Chinese (Traditional)": "",
    //   "French": "",
    //   "German": "",
    //   "Japanese": "",
    //   "Korean": "",
    //   "Chinese (Simplified)": "",
    //   "Spanish": "",
    //   "Sugondese": "skibidi gyat edge rizz ligma bofa Candice deez nuts bruh uwu duolussy ohio",
    //   "Vietnamese": ""
    // },
    // {
    //   "English": "",
    //   "Chinese (Traditional)": "",
    //   "French": "",
    //   "German": "",
    //   "Japanese": "",
    //   "Korean": "",
    //   "Chinese (Simplified)": "",
    //   "Spanish": "",
    //   "Sugondese": "skibidi gyat edge rizz ligma bofa Candice deez nuts bruh uwu duolussy ohio",
    //   "Vietnamese": ""
    // },
    // {
    //   "English": "",
    //   "Chinese (Traditional)": "",
    //   "French": "",
    //   "German": "",
    //   "Japanese": "",
    //   "Korean": "",
    //   "Chinese (Simplified)": "",
    //   "Spanish": "",
    //   "Sugondese": "skibidi gyat edge rizz ligma bofa Candice deez nuts bruh uwu duolussy ohio",
    //   "Vietnamese": ""
    // },
    // {
    //   "English": "",
    //   "Chinese (Traditional)": "",
    //   "French": "",
    //   "German": "",
    //   "Japanese": "",
    //   "Korean": "",
    //   "Chinese (Simplified)": "",
    //   "Spanish": "",
    //   "Sugondese": "skibidi gyat edge rizz ligma bofa Candice deez nuts bruh uwu duolussy ohio",
    //   "Vietnamese": ""
    // },
    // {
    //   "English": "",
    //   "Chinese (Traditional)": "",
    //   "French": "",
    //   "German": "",
    //   "Japanese": "",
    //   "Korean": "",
    //   "Chinese (Simplified)": "",
    //   "Spanish": "",
    //   "Sugondese": "skibidi gyat edge rizz ligma bofa Candice deez nuts bruh uwu duolussy ohio",
    //   "Vietnamese": ""
    // },
    // {
    //   "English": "",
    //   "Chinese (Traditional)": "",
    //   "French": "",
    //   "German": "",
    //   "Japanese": "",
    //   "Korean": "",
    //   "Chinese (Simplified)": "",
    //   "Spanish": "",
    //   "Sugondese": "skibidi gyat edge rizz ligma bofa Candice deez nuts bruh uwu duolussy ohio",
    //   "Vietnamese": ""
    // },
    // {
    //   "English": "",
    //   "Chinese (Traditional)": "",
    //   "French": "",
    //   "German": "",
    //   "Japanese": "",
    //   "Korean": "",
    //   "Chinese (Simplified)": "",
    //   "Spanish": "",
    //   "Sugondese": "skibidi gyat edge rizz ligma bofa Candice deez nuts bruh uwu duolussy ohio",
    //   "Vietnamese": ""
    // },
    // {
    //   "English": "",
    //   "Chinese (Traditional)": "",
    //   "French": "",
    //   "German": "",
    //   "Japanese": "",
    //   "Korean": "",
    //   "Chinese (Simplified)": "",
    //   "Spanish": "",
    //   "Sugondese": "skibidi gyat edge rizz ligma bofa Candice deez nuts bruh uwu duolussy ohio",
    //   "Vietnamese": ""
    // },
    // {
    //   "English": "",
    //   "Chinese (Traditional)": "",
    //   "French": "",
    //   "German": "",
    //   "Japanese": "",
    //   "Korean": "",
    //   "Chinese (Simplified)": "",
    //   "Spanish": "",
    //   "Sugondese": "skibidi gyat edge rizz ligma bofa Candice deez nuts bruh uwu duolussy ohio",
    //   "Vietnamese": ""
    // },
    // {
    //   "English": "",
    //   "Chinese (Traditional)": "",
    //   "French": "",
    //   "German": "",
    //   "Japanese": "",
    //   "Korean": "",
    //   "Chinese (Simplified)": "",
    //   "Spanish": "",
    //   "Sugondese": "skibidi gyat edge rizz ligma bofa Candice deez nuts bruh uwu duolussy ohio",
    //   "Vietnamese": ""
    // },
    // {
    //   "English": "",
    //   "Chinese (Traditional)": "",
    //   "French": "",
    //   "German": "",
    //   "Japanese": "",
    //   "Korean": "",
    //   "Chinese (Simplified)": "",
    //   "Spanish": "",
    //   "Sugondese": "skibidi gyat edge rizz ligma bofa Candice deez nuts bruh uwu duolussy ohio",
    //   "Vietnamese": ""
    // },
    // {
    //   "English": "",
    //   "Chinese (Traditional)": "",
    //   "French": "",
    //   "German": "",
    //   "Japanese": "",
    //   "Korean": "",
    //   "Chinese (Simplified)": "",
    //   "Spanish": "",
    //   "Sugondese": "skibidi gyat edge rizz ligma bofa Candice deez nuts bruh uwu duolussy ohio",
    //   "Vietnamese": ""
    // },
    // {
    //   "English": "",
    //   "Chinese (Traditional)": "",
    //   "French": "",
    //   "German": "",
    //   "Japanese": "",
    //   "Korean": "",
    //   "Chinese (Simplified)": "",
    //   "Spanish": "",
    //   "Sugondese": "skibidi gyat edge rizz ligma bofa Candice deez nuts bruh uwu duolussy ohio",
    //   "Vietnamese": ""
    // },
    // {
    //   "English": "",
    //   "Chinese (Traditional)": "",
    //   "French": "",
    //   "German": "",
    //   "Japanese": "",
    //   "Korean": "",
    //   "Chinese (Simplified)": "",
    //   "Spanish": "",
    //   "Sugondese": "skibidi gyat edge rizz ligma bofa Candice deez nuts bruh uwu duolussy ohio",
    //   "Vietnamese": ""
    // },
    // {
    //   "English": "",
    //   "Chinese (Traditional)": "",
    //   "French": "",
    //   "German": "",
    //   "Japanese": "",
    //   "Korean": "",
    //   "Chinese (Simplified)": "",
    //   "Spanish": "",
    //   "Sugondese": "skibidi gyat edge rizz ligma bofa Candice deez nuts bruh uwu duolussy ohio",
    //   "Vietnamese": ""
    // },
    // {
    //   "English": "",
    //   "Chinese (Traditional)": "",
    //   "French": "",
    //   "German": "",
    //   "Japanese": "",
    //   "Korean": "",
    //   "Chinese (Simplified)": "",
    //   "Spanish": "",
    //   "Sugondese": "skibidi gyat edge rizz ligma bofa Candice deez nuts bruh uwu duolussy ohio",
    //   "Vietnamese": ""
    // }
  ]
}
